pybenparallels/__init__.py
pybenparallels/__main__.py
pybenparallels/parallels_utils.py
pybenparallels-1.1.1.dist-info/licenses/LICENSE
pybenparallels-1.1.1.dist-info/METADATA
pybenparallels-1.1.1.dist-info/WHEEL
pybenparallels-1.1.1.dist-info/top_level.txt
pybenparallels-1.1.1.dist-info/RECORD
