Metadata-Version: 2.4
Name: pybenparallels
Version: 1.1.1
Summary: PyBEN Parallels repository is an easy to use python utility class for Parallels server solution
Author: Ben Moskovitch
Author-email: Ben Moskovitch <darkflameben@gmail.com>
Maintainer-email: Ben Moskovitch <darkflameben@gmail.com>
License-Expression: MIT
Project-URL: Homepage, https://github.com/DarkFlameBEN/pybenparallels.git
Keywords: python,parallels,utils,utilities,automation,automation-tools
Classifier: Development Status :: 5 - Production/Stable
Classifier: Intended Audience :: Developers
Classifier: Topic :: Software Development :: Libraries
Classifier: Operating System :: OS Independent
Classifier: Programming Language :: Python :: 3.8
Classifier: Programming Language :: Python :: 3.9
Classifier: Programming Language :: Python :: 3.10
Classifier: Programming Language :: Python :: 3.11
Classifier: Programming Language :: Python :: 3.12
Classifier: Programming Language :: Python :: 3.13
Requires-Python: >=3.8
License-File: LICENSE
Requires-Dist: pybenutils>=7.2.0
Dynamic: license-file
